simplifier/__index__.py
simplifier-0.0.0.dist-info/METADATA
simplifier-0.0.0.dist-info/WHEEL
simplifier-0.0.0.dist-info/top_level.txt
simplifier-0.0.0.dist-info/RECORD
