Metadata-Version: 2.1
Name: simplifier
Version: 0.0.0
Summary: Coming soon
Author: austinjp
Project-URL: Homepage, https://github.com/scout-ac/simplifier
Project-URL: Repository, https://github.com/scout-ac/simplifier.git
